leaderboard/__init__.py
leaderboard/competition_ranking_leaderboard.py
leaderboard/leaderboard.py
leaderboard/tie_ranking_leaderboard.py
ninchanese_leaderboard-3.7.4.dist-info/LICENSE.txt
ninchanese_leaderboard-3.7.4.dist-info/METADATA
ninchanese_leaderboard-3.7.4.dist-info/WHEEL
ninchanese_leaderboard-3.7.4.dist-info/top_level.txt
ninchanese_leaderboard-3.7.4.dist-info/RECORD
