Metadata-Version: 2.1
Name: ninchanese-leaderboard
Version: 3.7.4
Summary: Leaderboards backed by Redis in Python
Home-page: https://github.com/agoragames/leaderboard-python
Author: David Czarnecki
Author-email: dczarnecki@agoragames.com
License: LICENSE.txt
Keywords: python,redis,leaderboard
Platform: UNKNOWN
Classifier: Development Status :: 5 - Production/Stable
Classifier: License :: OSI Approved :: MIT License
Classifier: Intended Audience :: Developers
Classifier: Operating System :: POSIX
Classifier: Topic :: Communications
Classifier: Topic :: System :: Distributed Computing
Classifier: Topic :: Software Development :: Libraries :: Python Modules
Classifier: Programming Language :: Python
Classifier: Programming Language :: Python :: 2.7
Classifier: Programming Language :: Python :: 3
Classifier: Topic :: Software Development :: Libraries
Requires-Dist: redis (>=3)
